README.rst
setup.py
amanwa31/__init__.py
amanwa31/decorators.py
amanwa31/exceptions.py
amanwa31/handlers.py
amanwa31/handlers_test.py
amanwa31/middleware.py
amanwa31/middleware_test.py
amanwa31/response.py
amanwa31/router.py
amanwa31/router_test.py
amanwa31.egg-info/PKG-INFO
amanwa31.egg-info/SOURCES.txt
amanwa31.egg-info/dependency_links.txt
amanwa31.egg-info/not-zip-safe
amanwa31.egg-info/requires.txt
amanwa31.egg-info/top_level.txt
amanwa31/webapp3_extras/__init__.py
amanwa31/webapp3_extras/auth.py
amanwa31/webapp3_extras/i18n.py
amanwa31/webapp3_extras/jinja2.py
amanwa31/webapp3_extras/json.py
amanwa31/webapp3_extras/local.py
amanwa31/webapp3_extras/mako.py
amanwa31/webapp3_extras/routes.py
amanwa31/webapp3_extras/securecookie.py
amanwa31/webapp3_extras/security.py
amanwa31/webapp3_extras/sessions.py
amanwa31/webapp3_extras/xsrf.py
amanwa31/webapp3_extras/appengine/__init__.py
amanwa31/webapp3_extras/appengine/sessions_memcache.py
amanwa31/webapp3_extras/appengine/sessions_ndb.py
amanwa31/webapp3_extras/appengine/users.py
amanwa31/webapp3_extras/appengine/auth/__init__.py
amanwa31/webapp3_extras/appengine/auth/models.py